cowpoke/__init__.py
cowpoke/__main__.py
cowpoke/autoFill.py
cowpoke/build.py
cowpoke/config.py
cowpoke/extract.py
cowpoke/mapping.py
cowpoke/stats.py
cowpoke/utils.py
cowpoke/visualize.py
cowpoke-0.0.2.dist-info/LICENSE
cowpoke-0.0.2.dist-info/METADATA
cowpoke-0.0.2.dist-info/WHEEL
cowpoke-0.0.2.dist-info/top_level.txt
cowpoke-0.0.2.dist-info/RECORD
