Metadata-Version: 2.2
Name: cowpoke
Version: 0.0.2
Summary: Code in support of the 'Cooking with Python and KBpedia' (CWPK) series
Home-page: https://github.com/Cognonto/cowpoke
Author: Michael K Bergman
Author-email: mike@mkbergman.com
Project-URL: CWPK blog series, https://www.mkbergman.com/cooking-with-python-and-kbpedia/
Project-URL: CWPK Jupyter notebooks, https://github.com/Cognonto/CWPK
Project-URL: KBpedia, https://kbpedia.org/
Project-URL: Source, https://github.com/Cognonto/cowpoke/
Keywords: KBpedia,knowledge graph,build,extract
Classifier: Programming Language :: Python :: 3
Classifier: License :: OSI Approved :: MIT License
Classifier: Operating System :: OS Independent
Requires-Python: >=3.6
License-File: LICENSE
Dynamic: author
Dynamic: author-email
Dynamic: classifier
Dynamic: description
Dynamic: description-content-type
Dynamic: home-page
Dynamic: keywords
Dynamic: project-url
Dynamic: requires-python
Dynamic: summary
